morm/__init__.py
morm/admin.py
morm/ctx.py
morm/db.py
morm/dt.py
morm/exceptions.py
morm/meta.py
morm/migration.py
morm/model.py
morm/pg_models.py
morm/q.py
morm/utils.py
morm/version.py
morm/void.py
morm/fields/__init__.py
morm/fields/common.py
morm/fields/field.py
morm-2.8.1.data/scripts/init_fap
morm-2.8.1.data/scripts/morm_admin
morm-2.8.1.dist-info/licenses/LICENSE
morm-2.8.1.dist-info/METADATA
morm-2.8.1.dist-info/WHEEL
morm-2.8.1.dist-info/top_level.txt
morm-2.8.1.dist-info/RECORD
